[
  {
    "date": "2026-05-18",
    "country": "COD",
    "region": "Mongbalu",
    "province": "Ituri",
    "new_cases": 1,
    "new_deaths": 0,
    "suspected_cases": 302,
    "suspected_deaths": 74,
    "source": "WHO AFRO Weekly External Situation Report"
  },
  {
    "date": "2026-05-18",
    "country": "COD",
    "region": "Nyakunde",
    "province": "Ituri",
    "new_cases": 4,
    "new_deaths": 0,
    "suspected_cases": 14,
    "suspected_deaths": 1,
    "source": "WHO AFRO Weekly External Situation Report"
  },
  {
    "date": "2026-05-18",
    "country": "COD",
    "region": "Rwampara",
    "province": "Ituri",
    "new_cases": 19,
    "new_deaths": 3,
    "suspected_cases": 136,
    "suspected_deaths": 38,
    "source": "WHO AFRO Weekly External Situation Report"
  },
  {
    "date": "2026-05-18",
    "country": "COD",
    "region": "Bunia",
    "province": "Ituri",
    "new_cases": 6,
    "new_deaths": 1,
    "suspected_cases": 61,
    "suspected_deaths": 18,
    "source": "WHO AFRO Weekly External Situation Report"
  },
  {
    "date": "2026-05-18",
    "country": "COD",
    "region": "Butembo",
    "province": "Nord-Kivu",
    "new_cases": 1,
    "new_deaths": 0,
    "suspected_cases": 1,
    "suspected_deaths": 0,
    "source": "WHO AFRO Weekly External Situation Report"
  },
  {
    "date": "2026-05-18",
    "country": "COD",
    "region": "Katwa",
    "province": "Nord-Kivu",
    "new_cases": 1,
    "new_deaths": 0,
    "suspected_cases": 1,
    "suspected_deaths": 0,
    "source": "WHO AFRO Weekly External Situation Report"
  },
  {
    "date": "2026-05-18",
    "country": "COD",
    "region": "Goma",
    "province": "Nord-Kivu",
    "new_cases": 1,
    "new_deaths": 0,
    "suspected_cases": 1,
    "suspected_deaths": 0,
    "source": "WHO AFRO Weekly External Situation Report"
  },
  {
    "date": "2026-05-24",
    "country": "COD",
    "region": "Mongbalu",
    "province": "Ituri",
    "new_cases": 8,
    "new_deaths": 2,
    "suspected_cases": 415,
    "suspected_deaths": 98,
    "source": "WHO AFRO Weekly External Situation Report"
  },
  {
    "date": "2026-05-24",
    "country": "COD",
    "region": "Nyakunde",
    "province": "Ituri",
    "new_cases": 7,
    "new_deaths": 1,
    "suspected_cases": 22,
    "suspected_deaths": 2,
    "source": "WHO AFRO Weekly External Situation Report"
  },
  {
    "date": "2026-05-24",
    "country": "COD",
    "region": "Rwampara",
    "province": "Ituri",
    "new_cases": 31,
    "new_deaths": 5,
    "suspected_cases": 178,
    "suspected_deaths": 52,
    "source": "WHO AFRO Weekly External Situation Report"
  },
  {
    "date": "2026-05-24",
    "country": "COD",
    "region": "Bunia",
    "province": "Ituri",
    "new_cases": 9,
    "new_deaths": 2,
    "suspected_cases": 89,
    "suspected_deaths": 24,
    "source": "WHO AFRO Weekly External Situation Report"
  },
  {
    "date": "2026-05-24",
    "country": "COD",
    "region": "Butembo",
    "province": "Nord-Kivu",
    "new_cases": 2,
    "new_deaths": 0,
    "suspected_cases": 3,
    "suspected_deaths": 0,
    "source": "WHO AFRO Weekly External Situation Report"
  },
  {
    "date": "2026-05-24",
    "country": "COD",
    "region": "Katwa",
    "province": "Nord-Kivu",
    "new_cases": 1,
    "new_deaths": 0,
    "suspected_cases": 2,
    "suspected_deaths": 0,
    "source": "WHO AFRO Weekly External Situation Report"
  },
  {
    "date": "2026-05-24",
    "country": "COD",
    "region": "Goma",
    "province": "Nord-Kivu",
    "new_cases": 2,
    "new_deaths": 0,
    "suspected_cases": 3,
    "suspected_deaths": 0,
    "source": "WHO AFRO Weekly External Situation Report"
  },
  {
    "date": "2026-05-24",
    "country": "UGA",
    "region": "Kampala",
    "province": "Kampala",
    "new_cases": 7,
    "new_deaths": 1,
    "suspected_cases": 0,
    "suspected_deaths": 0,
    "source": "WHO AFRO Weekly External Situation Report"
  },
  {
    "date": "2026-05-31",
    "country": "COD",
    "region": "Mongbalu",
    "province": "Ituri",
    "new_cases": 12,
    "new_deaths": 3,
    "suspected_cases": 560,
    "suspected_deaths": 128,
    "source": "WHO AFRO Weekly External Situation Report"
  },
  {
    "date": "2026-05-31",
    "country": "COD",
    "region": "Nyakunde",
    "province": "Ituri",
    "new_cases": 10,
    "new_deaths": 2,
    "suspected_cases": 32,
    "suspected_deaths": 3,
    "source": "WHO AFRO Weekly External Situation Report"
  },
  {
    "date": "2026-05-31",
    "country": "COD",
    "region": "Rwampara",
    "province": "Ituri",
    "new_cases": 44,
    "new_deaths": 7,
    "suspected_cases": 245,
    "suspected_deaths": 68,
    "source": "WHO AFRO Weekly External Situation Report"
  },
  {
    "date": "2026-05-31",
    "country": "COD",
    "region": "Bunia",
    "province": "Ituri",
    "new_cases": 13,
    "new_deaths": 3,
    "suspected_cases": 125,
    "suspected_deaths": 33,
    "source": "WHO AFRO Weekly External Situation Report"
  },
  {
    "date": "2026-05-31",
    "country": "COD",
    "region": "Butembo",
    "province": "Nord-Kivu",
    "new_cases": 3,
    "new_deaths": 0,
    "suspected_cases": 6,
    "suspected_deaths": 1,
    "source": "WHO AFRO Weekly External Situation Report"
  },
  {
    "date": "2026-05-31",
    "country": "COD",
    "region": "Katwa",
    "province": "Nord-Kivu",
    "new_cases": 2,
    "new_deaths": 0,
    "suspected_cases": 5,
    "suspected_deaths": 1,
    "source": "WHO AFRO Weekly External Situation Report"
  },
  {
    "date": "2026-05-31",
    "country": "COD",
    "region": "Goma",
    "province": "Nord-Kivu",
    "new_cases": 4,
    "new_deaths": 1,
    "suspected_cases": 8,
    "suspected_deaths": 1,
    "source": "WHO AFRO Weekly External Situation Report"
  },
  {
    "date": "2026-05-31",
    "country": "UGA",
    "region": "Kampala",
    "province": "Kampala",
    "new_cases": 11,
    "new_deaths": 2,
    "suspected_cases": 1,
    "suspected_deaths": 0,
    "source": "WHO AFRO Weekly External Situation Report"
  },
  {
    "date": "2026-06-07",
    "country": "COD",
    "region": "Mongbalu",
    "province": "Ituri",
    "new_cases": 20,
    "new_deaths": 5,
    "suspected_cases": 740,
    "suspected_deaths": 168,
    "source": "WHO AFRO Weekly External Situation Report"
  },
  {
    "date": "2026-06-07",
    "country": "COD",
    "region": "Nyakunde",
    "province": "Ituri",
    "new_cases": 16,
    "new_deaths": 3,
    "suspected_cases": 48,
    "suspected_deaths": 5,
    "source": "WHO AFRO Weekly External Situation Report"
  },
  {
    "date": "2026-06-07",
    "country": "COD",
    "region": "Rwampara",
    "province": "Ituri",
    "new_cases": 62,
    "new_deaths": 11,
    "suspected_cases": 335,
    "suspected_deaths": 88,
    "source": "WHO AFRO Weekly External Situation Report"
  },
  {
    "date": "2026-06-07",
    "country": "COD",
    "region": "Bunia",
    "province": "Ituri",
    "new_cases": 19,
    "new_deaths": 5,
    "suspected_cases": 175,
    "suspected_deaths": 46,
    "source": "WHO AFRO Weekly External Situation Report"
  },
  {
    "date": "2026-06-07",
    "country": "COD",
    "region": "Butembo",
    "province": "Nord-Kivu",
    "new_cases": 5,
    "new_deaths": 1,
    "suspected_cases": 10,
    "suspected_deaths": 2,
    "source": "WHO AFRO Weekly External Situation Report"
  },
  {
    "date": "2026-06-07",
    "country": "COD",
    "region": "Katwa",
    "province": "Nord-Kivu",
    "new_cases": 3,
    "new_deaths": 0,
    "suspected_cases": 8,
    "suspected_deaths": 2,
    "source": "WHO AFRO Weekly External Situation Report"
  },
  {
    "date": "2026-06-07",
    "country": "COD",
    "region": "Goma",
    "province": "Nord-Kivu",
    "new_cases": 7,
    "new_deaths": 1,
    "suspected_cases": 14,
    "suspected_deaths": 2,
    "source": "WHO AFRO Weekly External Situation Report"
  },
  {
    "date": "2026-06-07",
    "country": "UGA",
    "region": "Kampala",
    "province": "Kampala",
    "new_cases": 16,
    "new_deaths": 3,
    "suspected_cases": 3,
    "suspected_deaths": 1,
    "source": "WHO AFRO Weekly External Situation Report"
  },
  {
    "date": "2026-06-07",
    "country": "UGA",
    "region": "Kisoro",
    "province": "Kisoro",
    "new_cases": 2,
    "new_deaths": 0,
    "suspected_cases": 5,
    "suspected_deaths": 1,
    "source": "WHO AFRO Weekly External Situation Report"
  },
  {
    "date": "2026-06-07",
    "country": "UGA",
    "region": "Arua",
    "province": "Arua",
    "new_cases": 1,
    "new_deaths": 0,
    "suspected_cases": 8,
    "suspected_deaths": 2,
    "source": "WHO AFRO Weekly External Situation Report"
  },
  {
    "date": "2026-06-07",
    "country": "UGA",
    "region": "Bundibugyo",
    "province": "Bundibugyo",
    "new_cases": 1,
    "new_deaths": 0,
    "suspected_cases": 6,
    "suspected_deaths": 1,
    "source": "WHO AFRO Weekly External Situation Report"
  },
  {
    "date": "2026-06-07",
    "country": "UGA",
    "region": "Kanungu",
    "province": "Kanungu",
    "new_cases": 1,
    "new_deaths": 0,
    "suspected_cases": 4,
    "suspected_deaths": 0,
    "source": "WHO AFRO Weekly External Situation Report"
  }
]